{
    "datoGeneral": {
        "idHojaVida": 178729.0,
        "idProcesoElectoral": 113.0,
        "idTipoEleccion": 6.0,
        "carneExtranjeria": null,
        "numeroDocumento": "72544321",
        "nombres": "YOSELIN KAREN",
        "apellidoPaterno": "RIVERA",
        "apellidoMaterno": "BERNABE",
        "sexo": "2",
        "feNacimiento": "28/03/1998",
        "paisNacimiento": "PERÚ",
        "ubigeoNacimiento": "110301",
        "naciDepartamento": "JUNIN",
        "naciProvincia": "JAUJA",
        "naciDistrito": "JAUJA",
        "ubigeoDomicilio": "110334",
        "domiDepartamento": "JUNIN",
        "domiProvincia": "JAUJA",
        "domiDistrito": "YAUYOS",
        "domicilioDirecc": "JR. FRANCISCO CARLE 204",
        "ubigeoPostula": "110334",
        "postulaDepartamento": "JUNIN",
        "postulaProvincia": "JAUJA",
        "postulaDistrito": "YAUYOS",
        "rutaArchivo": "/Assets/Fotos-HojaVida/178729.jpg",
        "estado": "RECIBIDO",
        "idOrganizacionPolitica": 2716.0,
        "organizacionPolitica": "JUNIN RENACE",
        "numeroCandidato": 1.0,
        "cargo": [
            "REGIDOR DISTRITAL"
        ],
        "txFeTerminoRegistro": "15/06/2022 10:02:05",
        "txGuidFormatoHojaVida": "a96e6716-1a18-4df7-b9fe-4b4173fec432",
        "idSolicitudLista": 28650.0,
        "txComentario": null
    },
    "experienciaLaboral": [
        {
            "idHvExpeLaboral": 241444,
            "tengoExpeLaboral": "1",
            "itemExpeLaboral": 1,
            "centroTrabajo": "MUNICIPALIDAD DISTRITAL DE SINCOS",
            "ocupacionProfesion": "RESPONSABLE DE DEMUNA",
            "rucTrabajo": "20191873492",
            "direccionTrabajo": "PLAZA PRINCIPAL S/N",
            "anioTrabajoDesde": "2021",
            "anioTrabajoHasta": "2021",
            "ubigeoTrabajo": "110328",
            "trabajoPais": "PERÚ",
            "trabajoDepartamento": "JUNIN",
            "trabajoProvincia": "JAUJA",
            "trabajoDistrito": "SINCOS",
            "idHojaVida": 178729,
            "idEstado": 1,
            "estado": "ACTIVO (R)",
            "txComentario": null
        }
    ],
    "formacionAcademica": {
        "educacionBasica": {
            "idHvEduBasica": 213207,
            "tengoEduBasica": "SI",
            "eduPrimaria": "SI",
            "concluidoEduPrimaria": "SI",
            "eduSecundaria": "SI",
            "concluidoEduSecundaria": "SI",
            "idHojaVida": 178729,
            "idEstado": 1,
            "estado": "ACTIVO (R)"
        },
        "educacionTecnico": [],
        "educacionNoUniversitaria": [],
        "educacionUniversitaria": [
            {
                "idHvEduUniversitaria": 182297,
                "tengoEduUniversitaria": "SI",
                "itemEduUni": "1",
                "eduUniversitaria": "1",
                "universidad": "UNIVERSIDAD NACIONAL DEL CENTRO DEL PERÚ",
                "carreraUni": "Bachiller en Antropología",
                "concluidoEduUni": "SI",
                "egresadoEduUni": "SI",
                "bachillerEduUni": null,
                "anioBachiller": "2021",
                "tituloUni": null,
                "anioTitulo": null,
                "idEstado": 1,
                "estado": "ACTIVO (R)",
                "txComentario": null
            }
        ],
        "educacionPosgrado": [],
        "educacionPosgradoOtro": []
    },
    "trayectoria": {
        "cargoPartidario": [],
        "cargoEleccion": []
    },
    "renunciaEfectuada": [
        {
            "idHvRenunciaOp": 163884,
            "tengoRenunciaOp": "SI",
            "itemRenunciaop": 1,
            "idOrgPolRenunciaOp": 2218,
            "orgPolRenunciaOp": "PARTIDO POLITICO NACIONAL PERU LIBRE",
            "anioRenunciaOp": "2021",
            "idHojaVida": 178729,
            "idEstado": 1,
            "txComentario": null
        }
    ],
    "informacionAdicional": [],
    "declaracionJurada": {
        "ingreso": [
            {
                "idHvIngresos": 192902,
                "idTengoIngresos": "1",
                "tengoIngresos": "SI",
                "anioIngresos": "2021",
                "remuBrutaPublico": 0.0,
                "remuBrutaPrivado": 0.0,
                "rentaIndividualPublico": 0.0,
                "rentaIndividualPrivado": 8000.0,
                "otroIngresoPublico": 0.0,
                "otroIngresoPrivado": 0.0,
                "idHojaVida": 178729,
                "idEstado": 1,
                "totalIngresos": 8000.0
            }
        ],
        "bienInmueble": [],
        "bienMueble": [],
        "otroMueble": [],
        "titularidad": []
    },
    "sentenciaPenal": [],
    "sentenciaObliga": []
}