{
    "datoGeneral": {
        "idHojaVida": 160503.0,
        "idProcesoElectoral": 113.0,
        "idTipoEleccion": 6.0,
        "carneExtranjeria": null,
        "numeroDocumento": "75431840",
        "nombres": "VICTOR HUGO",
        "apellidoPaterno": "DIAZ",
        "apellidoMaterno": "CORTEGANA",
        "sexo": "1",
        "feNacimiento": "18/05/1995",
        "paisNacimiento": "PERÚ",
        "ubigeoNacimiento": "190103",
        "naciDepartamento": "PIURA",
        "naciProvincia": "PIURA",
        "naciDistrito": "CASTILLA",
        "ubigeoDomicilio": "240105",
        "domiDepartamento": "CALLAO",
        "domiProvincia": "CALLAO",
        "domiDistrito": "LA PERLA",
        "domicilioDirecc": "JR. UCAYALI 128",
        "ubigeoPostula": "240105",
        "postulaDepartamento": "CALLAO",
        "postulaProvincia": "CALLAO",
        "postulaDistrito": "LA PERLA",
        "rutaArchivo": "/Assets/Fotos-HojaVida/160503.jpg",
        "estado": "IMPROCEDENTE",
        "idOrganizacionPolitica": 2898.0,
        "organizacionPolitica": "FE EN EL PERU",
        "numeroCandidato": 9.0,
        "cargo": [
            "REGIDOR DISTRITAL"
        ],
        "txFeTerminoRegistro": "13/06/2022 16:10:03",
        "txGuidFormatoHojaVida": "837f6491-42d5-433d-aadf-1cf7a1c5654c",
        "idSolicitudLista": 26223.0,
        "txComentario": null
    },
    "experienciaLaboral": [
        {
            "idHvExpeLaboral": 235867,
            "tengoExpeLaboral": "1",
            "itemExpeLaboral": 1,
            "centroTrabajo": "AFINA PERU S.A.C.",
            "ocupacionProfesion": "ESPECIALISTA DE RENOVACIONES",
            "rucTrabajo": "20517584399",
            "direccionTrabajo": "AV. LARCO 880",
            "anioTrabajoDesde": "2019",
            "anioTrabajoHasta": "2022",
            "ubigeoTrabajo": "140115",
            "trabajoPais": "PERÚ",
            "trabajoDepartamento": "LIMA",
            "trabajoProvincia": "LIMA",
            "trabajoDistrito": "MIRAFLORES",
            "idHojaVida": 160503,
            "idEstado": 1,
            "estado": "ACTIVO (R)",
            "txComentario": null
        }
    ],
    "formacionAcademica": {
        "educacionBasica": {
            "idHvEduBasica": 208224,
            "tengoEduBasica": "SI",
            "eduPrimaria": "SI",
            "concluidoEduPrimaria": "SI",
            "eduSecundaria": "SI",
            "concluidoEduSecundaria": "SI",
            "idHojaVida": 160503,
            "idEstado": 1,
            "estado": "ACTIVO (R)"
        },
        "educacionTecnico": [],
        "educacionNoUniversitaria": [],
        "educacionUniversitaria": [
            {
                "idHvEduUniversitaria": 179665,
                "tengoEduUniversitaria": "SI",
                "itemEduUni": "1",
                "eduUniversitaria": "1",
                "universidad": "UNIVERSIDAD DE SAN MARTÍN DE PORRES",
                "carreraUni": "BACHILLER EN INGENIERÍA DE COMPUTACIÓN Y SISTEMAS",
                "concluidoEduUni": "SI",
                "egresadoEduUni": "SI",
                "bachillerEduUni": null,
                "anioBachiller": "2021",
                "tituloUni": null,
                "anioTitulo": null,
                "idEstado": 1,
                "estado": "ACTIVO (R)",
                "txComentario": null
            }
        ],
        "educacionPosgrado": [],
        "educacionPosgradoOtro": []
    },
    "trayectoria": {
        "cargoPartidario": [],
        "cargoEleccion": []
    },
    "renunciaEfectuada": [],
    "informacionAdicional": [],
    "declaracionJurada": {
        "ingreso": [
            {
                "idHvIngresos": 188880,
                "idTengoIngresos": "1",
                "tengoIngresos": "SI",
                "anioIngresos": "2021",
                "remuBrutaPublico": 0.0,
                "remuBrutaPrivado": 50000.0,
                "rentaIndividualPublico": 0.0,
                "rentaIndividualPrivado": 0.0,
                "otroIngresoPublico": 0.0,
                "otroIngresoPrivado": 0.0,
                "idHojaVida": 160503,
                "idEstado": 1,
                "totalIngresos": 50000.0
            }
        ],
        "bienInmueble": [],
        "bienMueble": [],
        "otroMueble": [],
        "titularidad": []
    },
    "sentenciaPenal": [],
    "sentenciaObliga": []
}