{
    "datoGeneral": {
        "idHojaVida": 168028.0,
        "idProcesoElectoral": 113.0,
        "idTipoEleccion": 5.0,
        "carneExtranjeria": null,
        "numeroDocumento": "40756436",
        "nombres": "JESUS NELIDA",
        "apellidoPaterno": "TORRES",
        "apellidoMaterno": "ZURITA",
        "sexo": "2",
        "feNacimiento": "25/12/1980",
        "paisNacimiento": "PERÚ",
        "ubigeoNacimiento": "061101",
        "naciDepartamento": "CAJAMARCA",
        "naciProvincia": "SAN IGNACIO",
        "naciDistrito": "SAN IGNACIO",
        "ubigeoDomicilio": "010702",
        "domiDepartamento": "AMAZONAS",
        "domiProvincia": "UTCUBAMBA",
        "domiDistrito": "CAJARURO",
        "domicilioDirecc": "SECTOR SAN FRANCISCO",
        "ubigeoPostula": "010700",
        "postulaDepartamento": "AMAZONAS",
        "postulaProvincia": "UTCUBAMBA",
        "postulaDistrito": " ",
        "rutaArchivo": "/Assets/Fotos-HojaVida/168028.jpg",
        "estado": "ADMITIDO",
        "idOrganizacionPolitica": 2878.0,
        "organizacionPolitica": "VICTORIA AMAZONENSE",
        "numeroCandidato": 2.0,
        "cargo": [
            "REGIDOR PROVINCIAL"
        ],
        "txFeTerminoRegistro": "10/06/2022 17:40:56",
        "txGuidFormatoHojaVida": "65e1fbcc-9ddf-49eb-8f04-4bc5aa20418d",
        "idSolicitudLista": 27234.0,
        "txComentario": null
    },
    "experienciaLaboral": [
        {
            "idHvExpeLaboral": 160893,
            "tengoExpeLaboral": "1",
            "itemExpeLaboral": 1,
            "centroTrabajo": "I.E. N° 17329",
            "ocupacionProfesion": "DOCENTE",
            "rucTrabajo": null,
            "direccionTrabajo": "CENTRO POBLADO SAN JUAN DE LA LIBERTAD- SANTA CLARA",
            "anioTrabajoDesde": "2022",
            "anioTrabajoHasta": "2022",
            "ubigeoTrabajo": "010702",
            "trabajoPais": "PERÚ",
            "trabajoDepartamento": "AMAZONAS",
            "trabajoProvincia": "UTCUBAMBA",
            "trabajoDistrito": "CAJARURO",
            "idHojaVida": 168028,
            "idEstado": 1,
            "estado": "ACTIVO (R)",
            "txComentario": null
        }
    ],
    "formacionAcademica": {
        "educacionBasica": {
            "idHvEduBasica": 140622,
            "tengoEduBasica": "SI",
            "eduPrimaria": "SI",
            "concluidoEduPrimaria": "SI",
            "eduSecundaria": "SI",
            "concluidoEduSecundaria": "SI",
            "idHojaVida": 168028,
            "idEstado": 1,
            "estado": "ACTIVO (R)"
        },
        "educacionTecnico": [],
        "educacionNoUniversitaria": [],
        "educacionUniversitaria": [
            {
                "idHvEduUniversitaria": 144624,
                "tengoEduUniversitaria": "SI",
                "itemEduUni": "2",
                "eduUniversitaria": "1",
                "universidad": "UNIVERSIDAD NACIONAL PEDRO RUÍZ GALLO",
                "carreraUni": "BACHILLER EN EDUCACION",
                "concluidoEduUni": "SI",
                "egresadoEduUni": "SI",
                "bachillerEduUni": null,
                "anioBachiller": "2009",
                "tituloUni": null,
                "anioTitulo": null,
                "idEstado": 1,
                "estado": "ACTIVO (R)",
                "txComentario": null
            },
            {
                "idHvEduUniversitaria": 144623,
                "tengoEduUniversitaria": "SI",
                "itemEduUni": "1",
                "eduUniversitaria": "1",
                "universidad": "UNIVERSIDAD NACIONAL PEDRO RUÍZ GALLO",
                "carreraUni": "LICENCIADO EN EDUCACION NIVEL PRIMARIO",
                "concluidoEduUni": "SI",
                "egresadoEduUni": "SI",
                "bachillerEduUni": null,
                "anioBachiller": "2010",
                "tituloUni": null,
                "anioTitulo": null,
                "idEstado": 1,
                "estado": "ACTIVO (R)",
                "txComentario": null
            }
        ],
        "educacionPosgrado": [],
        "educacionPosgradoOtro": []
    },
    "trayectoria": {
        "cargoPartidario": [
            {
                "idHvCargoPartidario": 136434,
                "tengoCargoPartidario": "SI",
                "itemCargoPartidario": 1,
                "idOrgPolCargoPartidario": 1452,
                "orgPolCargoPartidario": "JUNTOS POR AMAZONAS",
                "cargoPartidario": "SECRETARÍA REGIONAL DE CULTURA, DEPORTE, MOVILIZACIÓN Y PROPAGANDA",
                "anioCargoPartiDesde": "2013",
                "anioCargoPartiHasta": "2015",
                "idHojaVida": 168028,
                "idEstado": 1,
                "estado": "ACTIVO (R)",
                "txComentario": null
            }
        ],
        "cargoEleccion": []
    },
    "renunciaEfectuada": [
        {
            "idHvRenunciaOp": 137223,
            "tengoRenunciaOp": "SI",
            "itemRenunciaop": 2,
            "idOrgPolRenunciaOp": 1452,
            "orgPolRenunciaOp": "JUNTOS POR AMAZONAS",
            "anioRenunciaOp": "2015",
            "idHojaVida": 168028,
            "idEstado": 1,
            "txComentario": null
        },
        {
            "idHvRenunciaOp": 137222,
            "tengoRenunciaOp": "SI",
            "itemRenunciaop": 1,
            "idOrgPolRenunciaOp": 2277,
            "orgPolRenunciaOp": "SENTIMIENTO AMAZONENSE REGIONAL",
            "anioRenunciaOp": "2021",
            "idHojaVida": 168028,
            "idEstado": 1,
            "txComentario": null
        }
    ],
    "informacionAdicional": [],
    "declaracionJurada": {
        "ingreso": [
            {
                "idHvIngresos": 138969,
                "idTengoIngresos": "1",
                "tengoIngresos": "SI",
                "anioIngresos": "2021",
                "remuBrutaPublico": 34800.0,
                "remuBrutaPrivado": 0.0,
                "rentaIndividualPublico": 0.0,
                "rentaIndividualPrivado": 0.0,
                "otroIngresoPublico": 0.0,
                "otroIngresoPrivado": 0.0,
                "idHojaVida": 168028,
                "idEstado": 1,
                "totalIngresos": 34800.0
            }
        ],
        "bienInmueble": [],
        "bienMueble": [
            {
                "idHvBienMueble": 151658,
                "idTengoBienMueble": "1",
                "tengoBienMueble": "SI",
                "itemMueble": 2,
                "vehiculo": "REGISTRO DE PROPIEDAD VEHICULAR",
                "marca": null,
                "placa": "4930XM ",
                "valor": 4000.0,
                "modelo": null,
                "anio": null,
                "caracteristica": "MOTO LINEAL COLOR NEGRA",
                "comentario": null,
                "idHojaVida": 168028,
                "idEstado": 1
            },
            {
                "idHvBienMueble": 151657,
                "idTengoBienMueble": "1",
                "tengoBienMueble": "SI",
                "itemMueble": 1,
                "vehiculo": "REGISTRO DE PROPIEDAD VEHICULAR",
                "marca": null,
                "placa": "4715XM ",
                "valor": 4500.0,
                "modelo": null,
                "anio": null,
                "caracteristica": "MOTO LINIAL COLOR ROJA",
                "comentario": null,
                "idHojaVida": 168028,
                "idEstado": 1
            }
        ],
        "otroMueble": [],
        "titularidad": []
    },
    "sentenciaPenal": [],
    "sentenciaObliga": []
}