{
    "datoGeneral": {
        "idHojaVida": 174824.0,
        "idProcesoElectoral": 113.0,
        "idTipoEleccion": 4.0,
        "carneExtranjeria": null,
        "numeroDocumento": "21403292",
        "nombres": "GUSTAVO ENRIQUE",
        "apellidoPaterno": "SOTO",
        "apellidoMaterno": "LEVANO",
        "sexo": "1",
        "feNacimiento": "11/03/1957",
        "paisNacimiento": "PERÚ",
        "ubigeoNacimiento": "100101",
        "naciDepartamento": "ICA",
        "naciProvincia": "ICA",
        "naciDistrito": "ICA",
        "ubigeoDomicilio": "100101",
        "domiDepartamento": "ICA",
        "domiProvincia": "ICA",
        "domiDistrito": "ICA",
        "domicilioDirecc": "URB.NUEVA VILLA B-05",
        "ubigeoPostula": "100000",
        "postulaDepartamento": "ICA",
        "postulaProvincia": " ",
        "postulaDistrito": " ",
        "rutaArchivo": "/Assets/Fotos-HojaVida/174824.jpg",
        "estado": "INSCRITO",
        "idOrganizacionPolitica": 1366.0,
        "organizacionPolitica": "FUERZA POPULAR",
        "numeroCandidato": 1.0,
        "cargo": [
            "CONSEJERO REGIONAL",
            " CONSEJERO REGIONAL",
            " CONSEJERO REGIONAL",
            " CONSEJERO REGIONAL"
        ],
        "txFeTerminoRegistro": "14/06/2022 06:52:06",
        "txGuidFormatoHojaVida": "9147fa37-613c-4cd1-86c9-14f00f3c2ce1",
        "idSolicitudLista": 28159.0,
        "txComentario": null
    },
    "experienciaLaboral": [
        {
            "idHvExpeLaboral": 218425,
            "tengoExpeLaboral": "1",
            "itemExpeLaboral": 1,
            "centroTrabajo": "HOSPITAL SANTA MARIA DEL SOCORRO",
            "ocupacionProfesion": "MEDICO CIRUJANO",
            "rucTrabajo": "20181753120",
            "direccionTrabajo": "CALLE CASTROVIRREYNA 759-ICA",
            "anioTrabajoDesde": "1990",
            "anioTrabajoHasta": "0000",
            "ubigeoTrabajo": "100101",
            "trabajoPais": "PERÚ",
            "trabajoDepartamento": "ICA",
            "trabajoProvincia": "ICA",
            "trabajoDistrito": "ICA",
            "idHojaVida": 174824,
            "idEstado": 1,
            "estado": "ACTIVO (R)",
            "txComentario": null
        },
        {
            "idHvExpeLaboral": 218488,
            "tengoExpeLaboral": "1",
            "itemExpeLaboral": 2,
            "centroTrabajo": "CONSULTORIO PARTICULAR",
            "ocupacionProfesion": "MEDICO OTORRINOLARINGOLOGO",
            "rucTrabajo": "10214032924",
            "direccionTrabajo": "CALLE AYACUCHO 254",
            "anioTrabajoDesde": "1990",
            "anioTrabajoHasta": "0000",
            "ubigeoTrabajo": "100101",
            "trabajoPais": "PERÚ",
            "trabajoDepartamento": "ICA",
            "trabajoProvincia": "ICA",
            "trabajoDistrito": "ICA",
            "idHojaVida": 174824,
            "idEstado": 1,
            "estado": "ACTIVO (R)",
            "txComentario": null
        }
    ],
    "formacionAcademica": {
        "educacionBasica": {
            "idHvEduBasica": 192537,
            "tengoEduBasica": "SI",
            "eduPrimaria": "SI",
            "concluidoEduPrimaria": "SI",
            "eduSecundaria": "SI",
            "concluidoEduSecundaria": "SI",
            "idHojaVida": 174824,
            "idEstado": 1,
            "estado": "ACTIVO (R)"
        },
        "educacionTecnico": [],
        "educacionNoUniversitaria": [],
        "educacionUniversitaria": [
            {
                "idHvEduUniversitaria": 171548,
                "tengoEduUniversitaria": "SI",
                "itemEduUni": "1",
                "eduUniversitaria": "1",
                "universidad": "UNIVERSIDAD NACIONAL SAN LUIS GONZAGA DE ICA",
                "carreraUni": "MEDICO CIRUJANO",
                "concluidoEduUni": "SI",
                "egresadoEduUni": "SI",
                "bachillerEduUni": null,
                "anioBachiller": "1984",
                "tituloUni": null,
                "anioTitulo": null,
                "idEstado": 1,
                "estado": "ACTIVO (R)",
                "txComentario": null
            }
        ],
        "educacionPosgrado": [
            {
                "idHvPosgrado": 139793,
                "tengoPosgrado": "SI",
                "nuItemPosgrado": 1,
                "txCenEstudioPosgrado": "UNIVERSIDAD NACIONAL SAN LUIS GONZAGA DE ICA",
                "txEspecialidadPosgrado": "SALUD PUBLICA",
                "concluidoPosgrado": "NO",
                "egresadoPosgrado": null,
                "esMaestro": "SI",
                "esDoctor": null,
                "txAnioPosgrado": null,
                "idHojaVida": 174824,
                "idEstado": 1,
                "txEstado": "ACTIVO (R)",
                "fgRegistroManual": 1,
                "txComentario": "EN TRAMITE",
                "fgRegistro": null
            }
        ],
        "educacionPosgradoOtro": []
    },
    "trayectoria": {
        "cargoPartidario": [
            {
                "idHvCargoPartidario": 141284,
                "tengoCargoPartidario": "SI",
                "itemCargoPartidario": 1,
                "idOrgPolCargoPartidario": 340,
                "orgPolCargoPartidario": "FRENTE REGIONAL PROGRESISTA IQUEÑO",
                "cargoPartidario": "SECRETARIO DE DISCIPLINA Y ACCIÓN POLITICA",
                "anioCargoPartiDesde": "2006",
                "anioCargoPartiHasta": "2014",
                "idHojaVida": 174824,
                "idEstado": 1,
                "estado": "ACTIVO (R)",
                "txComentario": null
            }
        ],
        "cargoEleccion": [
            {
                "idHvcargoEleccion": 142905,
                "tengoCargoEleccion": "SI",
                "itemCargoEleccion": 2,
                "idOrgPolCargoElec": 340,
                "orgPolCargoElec": "FRENTE REGIONAL PROGRESISTA IQUEÑO",
                "idCargoEleccion": 9,
                "cargoEleccion": "REGIDOR PROVINCIAL",
                "anioCargoElecDesde": "2011",
                "anioCargoElecHasta": "2014",
                "idHojaVida": 174824,
                "idEstado": 1,
                "estado": "ACTIVO (R)",
                "txComentario": null
            },
            {
                "idHvcargoEleccion": 142906,
                "tengoCargoEleccion": "SI",
                "itemCargoEleccion": 1,
                "idOrgPolCargoElec": 1243,
                "orgPolCargoElec": "UNIDOS POR ICA",
                "idCargoEleccion": 9,
                "cargoEleccion": "REGIDOR PROVINCIAL",
                "anioCargoElecDesde": "2007",
                "anioCargoElecHasta": "2010",
                "idHojaVida": 174824,
                "idEstado": 1,
                "estado": "ACTIVO (R)",
                "txComentario": null
            }
        ]
    },
    "renunciaEfectuada": [
        {
            "idHvRenunciaOp": 157921,
            "tengoRenunciaOp": "SI",
            "itemRenunciaop": 2,
            "idOrgPolRenunciaOp": 340,
            "orgPolRenunciaOp": "FRENTE REGIONAL PROGRESISTA IQUEÑO",
            "anioRenunciaOp": "2014",
            "idHojaVida": 174824,
            "idEstado": 1,
            "txComentario": null
        },
        {
            "idHvRenunciaOp": 157920,
            "tengoRenunciaOp": "SI",
            "itemRenunciaop": 1,
            "idOrgPolRenunciaOp": 38,
            "orgPolRenunciaOp": "PARTIDO REGIONAL DE INTEGRACION",
            "anioRenunciaOp": "2017",
            "idHojaVida": 174824,
            "idEstado": 1,
            "txComentario": null
        }
    ],
    "informacionAdicional": [],
    "declaracionJurada": {
        "ingreso": [
            {
                "idHvIngresos": 179500,
                "idTengoIngresos": "1",
                "tengoIngresos": "SI",
                "anioIngresos": "2021",
                "remuBrutaPublico": 100432.0,
                "remuBrutaPrivado": 0.0,
                "rentaIndividualPublico": 0.0,
                "rentaIndividualPrivado": 44400.0,
                "otroIngresoPublico": 0.0,
                "otroIngresoPrivado": 0.0,
                "idHojaVida": 174824,
                "idEstado": 1,
                "totalIngresos": 144832.0
            }
        ],
        "bienInmueble": [
            {
                "idHvBienInmueble": 237962,
                "idTengoinmueble": "1",
                "tengoInmueble": "SI",
                "itemInmueble": 2,
                "tipoBienInmueble": "INMUBLE",
                "ubigeoInmueble": null,
                "inmueblePais": null,
                "inmuebleDepartamento": null,
                "inmuebleProvincia": null,
                "inmuebleDistrito": null,
                "inmuebleDireccion": "NUEVA VILLA MZ B LETRA 5 ICA - ICA - ICA",
                "comentario": "EL MONTO DEL AUTOVALUO CORRESPONDE AL PAGO DEL AUTOVALUO D LOS 2 PREDIOS DECLARADOS.",
                "inmuebleSunarp": "1",
                "inmuebleSunarpDesc": "SI",
                "partidaSunarp": "11002941",
                "fichaTomoSunarp": null,
                "autovaluo": 1029.52,
                "idHojaVida": 174824,
                "idEstado": 1,
                "flValor": "190305.47"
            },
            {
                "idHvBienInmueble": 223813,
                "idTengoinmueble": "1",
                "tengoInmueble": "SI",
                "itemInmueble": 1,
                "tipoBienInmueble": "REGISTRO DE PREDIOS",
                "ubigeoInmueble": null,
                "inmueblePais": null,
                "inmuebleDepartamento": null,
                "inmuebleProvincia": null,
                "inmuebleDistrito": null,
                "inmuebleDireccion": " ESTANCIA DE SANTA MARIA MZ C LOTE 46   ICA - ICA - ICA",
                "comentario": "EL MONTO DEL AUTOVALUO CORRESPONDE AL PAGO DEL AUTOVALUO D LOS 2 PREDIOS DECLARADOS.",
                "inmuebleSunarp": "1",
                "inmuebleSunarpDesc": "SI",
                "partidaSunarp": "11111402",
                "fichaTomoSunarp": null,
                "autovaluo": 1029.52,
                "idHojaVida": 174824,
                "idEstado": 1,
                "flValor": "23480.73"
            }
        ],
        "bienMueble": [
            {
                "idHvBienMueble": 186455,
                "idTengoBienMueble": "1",
                "tengoBienMueble": "SI",
                "itemMueble": 2,
                "vehiculo": "REGISTRO DE PROPIEDAD VEHICULAR",
                "marca": null,
                "placa": "B1U359 ",
                "valor": 18000.0,
                "modelo": null,
                "anio": null,
                "caracteristica": "TOYOTA YARIS XLI 1.3 GSL",
                "comentario": null,
                "idHojaVida": 174824,
                "idEstado": 1
            },
            {
                "idHvBienMueble": 186454,
                "idTengoBienMueble": "1",
                "tengoBienMueble": "SI",
                "itemMueble": 1,
                "vehiculo": "REGISTRO DE PROPIEDAD VEHICULAR",
                "marca": null,
                "placa": "A9X435 ",
                "valor": 10000.0,
                "modelo": null,
                "anio": null,
                "caracteristica": "TOYOTA COROLLA TERCEL M/T",
                "comentario": null,
                "idHojaVida": 174824,
                "idEstado": 1
            }
        ],
        "otroMueble": [],
        "titularidad": []
    },
    "sentenciaPenal": [],
    "sentenciaObliga": []
}