[
    {
        "idArchivo": 725936.0,
        "idTipoDocumento": null,
        "tipoDocumento": "DECLARACIÓN JURADA DE HOJA DE VIDA",
        "peso": "162.4 KB",
        "paginas": 4,
        "rutaDocumento": "E:\\FileServer\\SIJE_DOCS\\Documentos",
        "guidArchivoDeclara": "84cf638b-93fa-4e78-b379-8b4b61fd1688",
        "extension": ".pdf",
        "nombreArchivo": "84cf638b-93fa-4e78-b379-8b4b61fd1688.pdf"
    },
    {
        "idArchivo": 826483.0,
        "idTipoDocumento": null,
        "tipoDocumento": "DDJJ DE CONSENTIMIENTO DE PARTICIPACIÓN ",
        "peso": "410.72 KB",
        "paginas": 2,
        "rutaDocumento": "E:\\FileServer\\SIJE_DOCS\\Documentos",
        "guidArchivoDeclara": "ad6e5183-17ef-4dff-9b26-31ad8d3cd792",
        "extension": ".pdf",
        "nombreArchivo": "ad6e5183-17ef-4dff-9b26-31ad8d3cd792.pdf"
    },
    {
        "idArchivo": 826329.0,
        "idTipoDocumento": null,
        "tipoDocumento": "DDJJ DE NO TENER DEUDA DE REPARACIÓN CIVIL",
        "peso": "466.58 KB",
        "paginas": 2,
        "rutaDocumento": "E:\\FileServer\\SIJE_DOCS\\Documentos",
        "guidArchivoDeclara": "96798a7a-ce09-48e9-8710-9b974d43ab48",
        "extension": ".pdf",
        "nombreArchivo": "96798a7a-ce09-48e9-8710-9b974d43ab48.pdf"
    },
    {
        "idArchivo": 818182.0,
        "idTipoDocumento": null,
        "tipoDocumento": "COMPROBANTE DE PAGO",
        "peso": "92.52 KB",
        "paginas": 1,
        "rutaDocumento": "E:\\FileServer\\SIJE_DOCS\\Documentos",
        "guidArchivoDeclara": "68989adb-7788-4673-9e8b-36ed4cf720f1",
        "extension": ".pdf",
        "nombreArchivo": "68989adb-7788-4673-9e8b-36ed4cf720f1.pdf"
    }
]