[
    {
        "idArchivo": 922022.0,
        "idTipoDocumento": null,
        "tipoDocumento": "DECLARACIÓN JURADA DE HOJA DE VIDA",
        "peso": "162.83 KB",
        "paginas": 4,
        "rutaDocumento": "E:\\FileServer\\SIJE_DOCS\\Documentos",
        "guidArchivoDeclara": "d33170c3-72d9-485e-82e8-44638d3a38a1",
        "extension": ".pdf",
        "nombreArchivo": "d33170c3-72d9-485e-82e8-44638d3a38a1.pdf"
    },
    {
        "idArchivo": 922009.0,
        "idTipoDocumento": null,
        "tipoDocumento": "DDJJ DE CONSENTIMIENTO DE PARTICIPACIÓN ",
        "peso": "437.35 KB",
        "paginas": 2,
        "rutaDocumento": "E:\\FileServer\\SIJE_DOCS\\Documentos",
        "guidArchivoDeclara": "261e241a-c393-46b5-9cb3-7efec38e3505",
        "extension": ".pdf",
        "nombreArchivo": "261e241a-c393-46b5-9cb3-7efec38e3505.pdf"
    },
    {
        "idArchivo": 922010.0,
        "idTipoDocumento": null,
        "tipoDocumento": "DDJJ DE NO TENER DEUDA DE REPARACIÓN CIVIL",
        "peso": "496.14 KB",
        "paginas": 2,
        "rutaDocumento": "E:\\FileServer\\SIJE_DOCS\\Documentos",
        "guidArchivoDeclara": "7c194757-89fe-4130-9dff-0f6eb8f26359",
        "extension": ".pdf",
        "nombreArchivo": "7c194757-89fe-4130-9dff-0f6eb8f26359.pdf"
    },
    {
        "idArchivo": 428125.0,
        "idTipoDocumento": null,
        "tipoDocumento": "COMPROBANTE DE PAGO",
        "peso": "76.49 KB",
        "paginas": 1,
        "rutaDocumento": "E:\\FileServer\\SIJE_DOCS\\Documentos",
        "guidArchivoDeclara": "3551487c-4d5b-4c57-9c3b-726b5329bff5",
        "extension": ".pdf",
        "nombreArchivo": "3551487c-4d5b-4c57-9c3b-726b5329bff5.pdf"
    }
]