[
    {
        "idArchivo": 937963.0,
        "idTipoDocumento": null,
        "tipoDocumento": "DECLARACIÓN JURADA DE HOJA DE VIDA",
        "peso": "166.51 KB",
        "paginas": 4,
        "rutaDocumento": "E:\\FileServer\\SIJE_DOCS\\Documentos",
        "guidArchivoDeclara": "58a58e6b-3a26-4910-b640-24c48e9d9193",
        "extension": ".pdf",
        "nombreArchivo": "58a58e6b-3a26-4910-b640-24c48e9d9193.pdf"
    },
    {
        "idArchivo": 937968.0,
        "idTipoDocumento": null,
        "tipoDocumento": "DDJJ DE CONSENTIMIENTO DE PARTICIPACIÓN ",
        "peso": "427.05 KB",
        "paginas": 2,
        "rutaDocumento": "E:\\FileServer\\SIJE_DOCS\\Documentos",
        "guidArchivoDeclara": "7c5e6559-8bfb-45ef-b14e-e7d5402c89ee",
        "extension": ".pdf",
        "nombreArchivo": "7c5e6559-8bfb-45ef-b14e-e7d5402c89ee.pdf"
    },
    {
        "idArchivo": 937969.0,
        "idTipoDocumento": null,
        "tipoDocumento": "DDJJ DE NO TENER DEUDA DE REPARACIÓN CIVIL",
        "peso": "511.75 KB",
        "paginas": 2,
        "rutaDocumento": "E:\\FileServer\\SIJE_DOCS\\Documentos",
        "guidArchivoDeclara": "28454e81-9082-4d60-9568-617a2a976688",
        "extension": ".pdf",
        "nombreArchivo": "28454e81-9082-4d60-9568-617a2a976688.pdf"
    },
    {
        "idArchivo": 295736.0,
        "idTipoDocumento": null,
        "tipoDocumento": "COMPROBANTE DE PAGO",
        "peso": "220.15 KB",
        "paginas": 1,
        "rutaDocumento": "E:\\FileServer\\SIJE_DOCS\\Documentos",
        "guidArchivoDeclara": "00abc6f3-4dfa-473c-ba4d-3815c4dd5367",
        "extension": ".pdf",
        "nombreArchivo": "00abc6f3-4dfa-473c-ba4d-3815c4dd5367.pdf"
    }
]