[
    {
        "idArchivo": 591230.0,
        "idTipoDocumento": null,
        "tipoDocumento": "DECLARACIÓN JURADA DE HOJA DE VIDA",
        "peso": "163.62 KB",
        "paginas": 4,
        "rutaDocumento": "E:\\FileServer\\SIJE_DOCS\\Documentos",
        "guidArchivoDeclara": "630bf286-7c66-4127-b3fb-396160ab7538",
        "extension": ".pdf",
        "nombreArchivo": "630bf286-7c66-4127-b3fb-396160ab7538.pdf"
    },
    {
        "idArchivo": 591263.0,
        "idTipoDocumento": null,
        "tipoDocumento": "DDJJ DE CONSENTIMIENTO DE PARTICIPACIÓN ",
        "peso": "484.39 KB",
        "paginas": 2,
        "rutaDocumento": "E:\\FileServer\\SIJE_DOCS\\Documentos",
        "guidArchivoDeclara": "61149adf-6035-4cf4-acdd-ee0bf9dac0b5",
        "extension": ".pdf",
        "nombreArchivo": "61149adf-6035-4cf4-acdd-ee0bf9dac0b5.pdf"
    },
    {
        "idArchivo": 591265.0,
        "idTipoDocumento": null,
        "tipoDocumento": "DDJJ DE NO TENER DEUDA DE REPARACIÓN CIVIL",
        "peso": "594.25 KB",
        "paginas": 2,
        "rutaDocumento": "E:\\FileServer\\SIJE_DOCS\\Documentos",
        "guidArchivoDeclara": "a017e138-8851-4ca5-a806-af8d691fdf49",
        "extension": ".pdf",
        "nombreArchivo": "a017e138-8851-4ca5-a806-af8d691fdf49.pdf"
    },
    {
        "idArchivo": 487498.0,
        "idTipoDocumento": null,
        "tipoDocumento": "COMPROBANTE DE PAGO",
        "peso": "87.72 KB",
        "paginas": 1,
        "rutaDocumento": "E:\\FileServer\\SIJE_DOCS\\Documentos",
        "guidArchivoDeclara": "259b4a97-a6fc-4ec4-80e5-097561a42097",
        "extension": ".pdf",
        "nombreArchivo": "259b4a97-a6fc-4ec4-80e5-097561a42097.pdf"
    }
]