[
    {
        "idArchivo": 779922.0,
        "idTipoDocumento": null,
        "tipoDocumento": "DECLARACIÓN JURADA DE HOJA DE VIDA",
        "peso": "165.61 KB",
        "paginas": 5,
        "rutaDocumento": "E:\\FileServer\\SIJE_DOCS\\Documentos",
        "guidArchivoDeclara": "c64c1170-7e22-4b9f-838c-c59a8cedbe76",
        "extension": ".pdf",
        "nombreArchivo": "c64c1170-7e22-4b9f-838c-c59a8cedbe76.pdf"
    },
    {
        "idArchivo": 779932.0,
        "idTipoDocumento": null,
        "tipoDocumento": "DDJJ DE CONSENTIMIENTO DE PARTICIPACIÓN ",
        "peso": "346.02 KB",
        "paginas": 1,
        "rutaDocumento": "E:\\FileServer\\SIJE_DOCS\\Documentos",
        "guidArchivoDeclara": "0f7bb8cb-b0b6-4202-9360-3bba057bc502",
        "extension": ".pdf",
        "nombreArchivo": "0f7bb8cb-b0b6-4202-9360-3bba057bc502.pdf"
    },
    {
        "idArchivo": 779933.0,
        "idTipoDocumento": null,
        "tipoDocumento": "DDJJ DE NO TENER DEUDA DE REPARACIÓN CIVIL",
        "peso": "388.14 KB",
        "paginas": 1,
        "rutaDocumento": "E:\\FileServer\\SIJE_DOCS\\Documentos",
        "guidArchivoDeclara": "a0b3f13b-52aa-440a-8d34-6fc109e31d94",
        "extension": ".pdf",
        "nombreArchivo": "a0b3f13b-52aa-440a-8d34-6fc109e31d94.pdf"
    },
    {
        "idArchivo": 232416.0,
        "idTipoDocumento": null,
        "tipoDocumento": "COMPROBANTE DE PAGO",
        "peso": "49.6 KB",
        "paginas": 1,
        "rutaDocumento": "E:\\FileServer\\SIJE_DOCS\\Documentos",
        "guidArchivoDeclara": "9741c0ca-9875-49d2-9d43-7ad6c1e0a53e",
        "extension": ".pdf",
        "nombreArchivo": "9741c0ca-9875-49d2-9d43-7ad6c1e0a53e.pdf"
    },
    {
        "idArchivo": 779931.0,
        "idTipoDocumento": null,
        "tipoDocumento": "OTROSDOCUMENTOS SUSTENTATORIOS DECLARADOS EN LA HOJA DE VIDA",
        "peso": "4.61 MB",
        "paginas": 17,
        "rutaDocumento": "E:\\FileServer\\SIJE_DOCS\\Documentos",
        "guidArchivoDeclara": "8724808a-35a8-47de-ac22-dc9fedb16b04",
        "extension": ".pdf",
        "nombreArchivo": "8724808a-35a8-47de-ac22-dc9fedb16b04.pdf"
    }
]