{
    "datoGeneral": {
        "idExpediente": 154369.0,
        "codExpedienteExt": "ERM.2022006827",
        "codExpediente": "2022.07721.ERM.HYLS.INL.INS.00",
        "feRegistro": "13/06/2022",
        "idOrganizacionPolitica": 2857.0,
        "organizacionPolitica": "PARTIDO FRENTE DE LA ESPERANZA 2021",
        "departamento": "ANCASH",
        "provincia": "HUAYLAS",
        "distrito": "MATO",
        "idMateria": 27.0,
        "materia": "SOLICITUD DE INSCRIPCIÓN",
        "idJuradoElectoral": 1686.0,
        "juradoElectoral": "HUAYLAS",
        "idTipoExpediente": 13.0,
        "tipoExpediente": "INSCRIPCIÓN DE LISTAS",
        "estadoExped": "EN TRAMITE",
        "tipoEleccion": "MUNICIPAL DISTRITAL",
        "asunto": null,
        "procedencia": null,
        "txOrigen": "EXPEDIENTE ELECTRÓNICO",
        "txEstadoJNE": null,
        "expApelacion": null,
        "codExpedientePadre": null
    },
    "expedienteActuado": [
        {
            "idExpediente": 154369,
            "idNotificacion": 0,
            "txNombreArchivoAdicional": null,
            "txJuradoCreacion": "HUAYLAS",
            "txFechaDocumento": "07/06/2022 15:22:00",
            "txNroDocumento": "ERM.2022006827003",
            "txCodArchivo": "ERM.2022006827003",
            "txAsunto": "Solicitud de SOLICITUD DE INSCRIPCIÓN en INSCRIPCIÓN DE LISTAS",
            "txParteInteresada": null,
            "txFechaPublicacion": "07/06/2022 15:22:00",
            "txRutaDocumento": "https://plataformahistorico.jne.gob.pe/Tmp/Escritos/",
            "txTipoExpediente": "ESCRITO",
            "txEstadoExped": "REGISTRADO",
            "nuFolioInicial": 1,
            "nuFolioFinal": 1,
            "txOrigen": "FISICO",
            "txNombre": "ERM.2022006827003",
            "txExtension": "",
            "flPesoFirma": 0.0,
            "nuFolios": 0,
            "fileExist": false,
            "origenMpe": false,
            "archivoBase64": null,
            "txFeEnvioSolicitud": "06/07/2022"
        },
        {
            "idExpediente": 154369,
            "idNotificacion": 0,
            "txNombreArchivoAdicional": null,
            "txJuradoCreacion": "HUAYLAS",
            "txFechaDocumento": "07/06/2022 15:22:00",
            "txNroDocumento": "ERM.2022006827003D001",
            "txCodArchivo": "ERM.2022006827003D001",
            "txAsunto": null,
            "txParteInteresada": null,
            "txFechaPublicacion": "07/06/2022 15:22:00",
            "txRutaDocumento": "https://mpesije.jne.gob.pe/docs/202200054209.pdf",
            "txTipoExpediente": "CARGO RECEPCION DE SOLICITUD",
            "txEstadoExped": "REGISTRADO",
            "nuFolioInicial": 1,
            "nuFolioFinal": 1,
            "txOrigen": "DIGITAL",
            "txNombre": "202200054209.pdf",
            "txExtension": ".pdf",
            "flPesoFirma": 0.03,
            "nuFolios": 0,
            "fileExist": true,
            "origenMpe": false,
            "archivoBase64": null,
            "txFeEnvioSolicitud": "06/07/2022"
        },
        {
            "idExpediente": 154369,
            "idNotificacion": 0,
            "txNombreArchivoAdicional": null,
            "txJuradoCreacion": "HUAYLAS",
            "txFechaDocumento": "07/06/2022 15:22:00",
            "txNroDocumento": "ERM.2022006827003D002",
            "txCodArchivo": "ERM.2022006827003D002",
            "txAsunto": null,
            "txParteInteresada": null,
            "txFechaPublicacion": "07/06/2022 15:22:00",
            "txRutaDocumento": "https://mpesije.jne.gob.pe/docs/938753fc-0d4e-4976-b5b6-27cb4bd2394b.pdf",
            "txTipoExpediente": "Escrito",
            "txEstadoExped": "REGISTRADO",
            "nuFolioInicial": 5,
            "nuFolioFinal": 6,
            "txOrigen": "DIGITAL",
            "txNombre": "938753fc-0d4e-4976-b5b6-27cb4bd2394b.pdf",
            "txExtension": ".pdf",
            "flPesoFirma": 0.99,
            "nuFolios": 0,
            "fileExist": true,
            "origenMpe": false,
            "archivoBase64": null,
            "txFeEnvioSolicitud": "06/07/2022"
        },
        {
            "idExpediente": 154369,
            "idNotificacion": 0,
            "txNombreArchivoAdicional": null,
            "txJuradoCreacion": "HUAYLAS",
            "txFechaDocumento": "06/16/2022 19:55:00",
            "txNroDocumento": "ERM.2022006827002",
            "txCodArchivo": "ERM.2022006827002",
            "txAsunto": "CONSTANCIA DE PUBLICACION",
            "txParteInteresada": null,
            "txFechaPublicacion": "06/16/2022 19:55:00",
            "txRutaDocumento": "https://plataformahistorico.jne.gob.pe/Tmp/Escritos/",
            "txTipoExpediente": "ESCRITO",
            "txEstadoExped": "REGISTRADO",
            "nuFolioInicial": 1,
            "nuFolioFinal": 1,
            "txOrigen": "FISICO",
            "txNombre": "ERM.2022006827002",
            "txExtension": "",
            "flPesoFirma": 0.0,
            "nuFolios": 0,
            "fileExist": false,
            "origenMpe": false,
            "archivoBase64": null,
            "txFeEnvioSolicitud": "16/06/2022"
        },
        {
            "idExpediente": 154369,
            "idNotificacion": 0,
            "txNombreArchivoAdicional": null,
            "txJuradoCreacion": "HUAYLAS",
            "txFechaDocumento": "06/16/2022 19:55:00",
            "txNroDocumento": "ERM.2022006827002D001",
            "txCodArchivo": "ERM.2022006827002D001",
            "txAsunto": null,
            "txParteInteresada": null,
            "txFechaPublicacion": "06/16/2022 19:55:00",
            "txRutaDocumento": "https://mpesije.jne.gob.pe/docs/968cd462-bcad-4f54-8929-ac0c99b51485.pdf",
            "txTipoExpediente": "Escrito",
            "txEstadoExped": "REGISTRADO",
            "nuFolioInicial": 1,
            "nuFolioFinal": 2,
            "txOrigen": "DIGITAL",
            "txNombre": "968cd462-bcad-4f54-8929-ac0c99b51485.pdf",
            "txExtension": ".pdf",
            "flPesoFirma": 0.16,
            "nuFolios": 0,
            "fileExist": true,
            "origenMpe": false,
            "archivoBase64": null,
            "txFeEnvioSolicitud": "16/06/2022"
        },
        {
            "idExpediente": 154369,
            "idNotificacion": 0,
            "txNombreArchivoAdicional": null,
            "txJuradoCreacion": "HUAYLAS",
            "txFechaDocumento": "06/16/2022 19:55:00",
            "txNroDocumento": null,
            "txCodArchivo": null,
            "txAsunto": null,
            "txParteInteresada": null,
            "txFechaPublicacion": "06/16/2022 19:55:00",
            "txRutaDocumento": "https://mpesije.jne.gob.pe/docs/202200017585.pdf",
            "txTipoExpediente": "CARGO RECEPCION DE SOLICITUD",
            "txEstadoExped": "REGISTRADO",
            "nuFolioInicial": 1,
            "nuFolioFinal": 1,
            "txOrigen": "DIGITAL",
            "txNombre": "202200017585.pdf",
            "txExtension": ".pdf",
            "flPesoFirma": 0.03,
            "nuFolios": 0,
            "fileExist": true,
            "origenMpe": false,
            "archivoBase64": null,
            "txFeEnvioSolicitud": "16/06/2022"
        },
        {
            "idExpediente": 154369,
            "idNotificacion": 293403,
            "txNombreArchivoAdicional": null,
            "txJuradoCreacion": "HUAYLAS",
            "txFechaDocumento": "06/16/2022 19:19:53",
            "txNroDocumento": "NOTIFICACIÓN N° 22856-2022-HYLS",
            "txCodArchivo": "NOTIFICACIÓN N° 22856-2022-HYLS",
            "txAsunto": null,
            "txParteInteresada": "YATACO YATACO JORGE LUIS",
            "txFechaPublicacion": "06/16/2022 19:30:05",
            "txRutaDocumento": "https://plataformahistorico.jne.gob.pe/Tmp/notificaciones/firmadas/NOTIFICACIÓN N° 22856-2022-HYLS.pdf",
            "txTipoExpediente": "NOTIFICACIÓN",
            "txEstadoExped": "NOTIFICADO",
            "nuFolioInicial": 1,
            "nuFolioFinal": 0,
            "txOrigen": "ELECTRÓNICO",
            "txNombre": "NOTIFICACIÓN N° 22856-2022-HYLS",
            "txExtension": ".PDF",
            "flPesoFirma": 0.05,
            "nuFolios": 0,
            "fileExist": true,
            "origenMpe": false,
            "archivoBase64": null,
            "txFeEnvioSolicitud": "16/06/2022"
        },
        {
            "idExpediente": 154369,
            "idNotificacion": 0,
            "txNombreArchivoAdicional": null,
            "txJuradoCreacion": "HUAYLAS",
            "txFechaDocumento": "06/16/2022 00:00:00",
            "txNroDocumento": "RESOLUCION N° 00074-2022-JEE-HYLS/JNE",
            "txCodArchivo": "RESOLUCION N° 00074-2022-JEE-HYLS/JNE",
            "txAsunto": "INADMISIBLE SOLICITUD DE INSCRIPCIÓN",
            "txParteInteresada": null,
            "txFechaPublicacion": "06/16/2022 19:19:12",
            "txRutaDocumento": "https://plataformahistorico.jne.gob.pe/Tmp/Proyectos/353080.pdf",
            "txTipoExpediente": "PRONUNCIAMIENTO",
            "txEstadoExped": "PUBLICADO",
            "nuFolioInicial": 4,
            "nuFolioFinal": 0,
            "txOrigen": "ELECTRÓNICO",
            "txNombre": "RESOLUCION N° 00074-2022-JEE-HYLS/JNE",
            "txExtension": ".pdf",
            "flPesoFirma": 0.2,
            "nuFolios": 0,
            "fileExist": true,
            "origenMpe": false,
            "archivoBase64": null,
            "txFeEnvioSolicitud": "16/06/2022"
        },
        {
            "idExpediente": 154369,
            "idNotificacion": 0,
            "txNombreArchivoAdicional": null,
            "txJuradoCreacion": "HUAYLAS",
            "txFechaDocumento": "06/13/2022 13:54:00",
            "txNroDocumento": "ERM.2022006827001",
            "txCodArchivo": "ERM.2022006827001",
            "txAsunto": null,
            "txParteInteresada": null,
            "txFechaPublicacion": "06/13/2022 13:54:00",
            "txRutaDocumento": "https://plataformahistorico.jne.gob.pe/Tmp/Escritos/",
            "txTipoExpediente": "ESCRITO",
            "txEstadoExped": "REGISTRADO",
            "nuFolioInicial": 1,
            "nuFolioFinal": 1,
            "txOrigen": "FISICO",
            "txNombre": "ERM.2022006827001",
            "txExtension": "",
            "flPesoFirma": 0.0,
            "nuFolios": 0,
            "fileExist": false,
            "origenMpe": false,
            "archivoBase64": null,
            "txFeEnvioSolicitud": "13/06/2022"
        },
        {
            "idExpediente": 154369,
            "idNotificacion": 0,
            "txNombreArchivoAdicional": null,
            "txJuradoCreacion": "HUAYLAS",
            "txFechaDocumento": "06/13/2022 13:54:00",
            "txNroDocumento": "ERM.2022006827001D001",
            "txCodArchivo": "ERM.2022006827001D001",
            "txAsunto": null,
            "txParteInteresada": null,
            "txFechaPublicacion": "06/13/2022 13:54:00",
            "txRutaDocumento": "https://mpesije.jne.gob.pe/docs/202200007856.pdf",
            "txTipoExpediente": "CARGO RECEPCION DE SOLICITUD",
            "txEstadoExped": "REGISTRADO",
            "nuFolioInicial": 1,
            "nuFolioFinal": 1,
            "txOrigen": "DIGITAL",
            "txNombre": "202200007856.pdf",
            "txExtension": ".pdf",
            "flPesoFirma": 0.03,
            "nuFolios": 0,
            "fileExist": true,
            "origenMpe": false,
            "archivoBase64": null,
            "txFeEnvioSolicitud": "13/06/2022"
        },
        {
            "idExpediente": 154369,
            "idNotificacion": 0,
            "txNombreArchivoAdicional": null,
            "txJuradoCreacion": "HUAYLAS",
            "txFechaDocumento": "06/13/2022 13:54:00",
            "txNroDocumento": "ERM.2022006827001D002",
            "txCodArchivo": "ERM.2022006827001D002",
            "txAsunto": null,
            "txParteInteresada": null,
            "txFechaPublicacion": "06/13/2022 13:54:00",
            "txRutaDocumento": "https://mpesije.jne.gob.pe/docs/7171b79d-6986-447f-bc62-43fb46f52bf0.pdf",
            "txTipoExpediente": "Solicitud de inscripción",
            "txEstadoExped": "REGISTRADO",
            "nuFolioInicial": 2,
            "nuFolioFinal": 3,
            "txOrigen": "DIGITAL",
            "txNombre": "7171b79d-6986-447f-bc62-43fb46f52bf0.pdf",
            "txExtension": ".pdf",
            "flPesoFirma": 0.48,
            "nuFolios": 0,
            "fileExist": true,
            "origenMpe": false,
            "archivoBase64": null,
            "txFeEnvioSolicitud": "13/06/2022"
        },
        {
            "idExpediente": 154369,
            "idNotificacion": 0,
            "txNombreArchivoAdicional": null,
            "txJuradoCreacion": "HUAYLAS",
            "txFechaDocumento": "06/13/2022 13:54:00",
            "txNroDocumento": "ERM.2022006827001D003",
            "txCodArchivo": "ERM.2022006827001D003",
            "txAsunto": null,
            "txParteInteresada": null,
            "txFechaPublicacion": "06/13/2022 13:54:00",
            "txRutaDocumento": "https://mpesije.jne.gob.pe/docs/94fd67f5-c635-4580-b380-12c55c982721.pdf",
            "txTipoExpediente": "Acta interna",
            "txEstadoExped": "REGISTRADO",
            "nuFolioInicial": 101,
            "nuFolioFinal": 104,
            "txOrigen": "DIGITAL",
            "txNombre": "94fd67f5-c635-4580-b380-12c55c982721.pdf",
            "txExtension": ".pdf",
            "flPesoFirma": 44.82,
            "nuFolios": 0,
            "fileExist": true,
            "origenMpe": false,
            "archivoBase64": null,
            "txFeEnvioSolicitud": "13/06/2022"
        },
        {
            "idExpediente": 154369,
            "idNotificacion": 0,
            "txNombreArchivoAdicional": null,
            "txJuradoCreacion": "HUAYLAS",
            "txFechaDocumento": "06/13/2022 13:54:00",
            "txNroDocumento": "ERM.2022006827001D004",
            "txCodArchivo": "ERM.2022006827001D004",
            "txAsunto": null,
            "txParteInteresada": null,
            "txFechaPublicacion": "06/13/2022 13:54:00",
            "txRutaDocumento": "https://mpesije.jne.gob.pe/docs/f20fbd54-adc8-4d15-89a1-2787f96e0d1d.pdf",
            "txTipoExpediente": "Plan de gobierno",
            "txEstadoExped": "REGISTRADO",
            "nuFolioInicial": 8,
            "nuFolioFinal": 112,
            "txOrigen": "DIGITAL",
            "txNombre": "f20fbd54-adc8-4d15-89a1-2787f96e0d1d.pdf",
            "txExtension": ".pdf",
            "flPesoFirma": 0.7,
            "nuFolios": 0,
            "fileExist": true,
            "origenMpe": false,
            "archivoBase64": null,
            "txFeEnvioSolicitud": "13/06/2022"
        },
        {
            "idExpediente": 154369,
            "idNotificacion": 0,
            "txNombreArchivoAdicional": null,
            "txJuradoCreacion": "HUAYLAS",
            "txFechaDocumento": "06/13/2022 13:54:00",
            "txNroDocumento": "ERM.2022006827001D005",
            "txCodArchivo": "ERM.2022006827001D005",
            "txAsunto": null,
            "txParteInteresada": null,
            "txFechaPublicacion": "06/13/2022 13:54:00",
            "txRutaDocumento": "https://mpesije.jne.gob.pe/docs/dd5e4fc4-5208-46b7-8ef6-ec65df402418.pdf",
            "txTipoExpediente": "FORMATO RESUMEN PG/PT",
            "txEstadoExped": "REGISTRADO",
            "nuFolioInicial": 2,
            "nuFolioFinal": 114,
            "txOrigen": "DIGITAL",
            "txNombre": "dd5e4fc4-5208-46b7-8ef6-ec65df402418.pdf",
            "txExtension": ".pdf",
            "flPesoFirma": 0.47,
            "nuFolios": 0,
            "fileExist": true,
            "origenMpe": false,
            "archivoBase64": null,
            "txFeEnvioSolicitud": "13/06/2022"
        }
    ],
    "expedienteRelacionado": null,
    "expedientePersonero": [],
    "expedienteCandidato": [
        {
            "idExpediente": 154369.0,
            "idTipoEleccion": 6.0,
            "txCodExpedienteExt": "ERM.2022006827",
            "txNombres": "CIRILO",
            "txApellidoPaterno": "LETONA",
            "txApellidoMaterno": "MELGAREJO",
            "txDocumentoIdentidad": "08667397",
            "txRutaArchivo": "/Assets/Fotos-HojaVida/142930.jpg",
            "txFeNacimiento": "18/03/1965",
            "txSexo": "MASCULINO",
            "idEstadosCandPer": 3.0,
            "txEstado": "INADMISIBLE",
            "txDesignado": "NO",
            "idOrganizacionPolitica": 2857.0,
            "idHojaVida": 142930.0,
            "txOrganizacionPolitica": "PARTIDO FRENTE DE LA ESPERANZA 2021",
            "txUbigeoPostula": "ANCASH",
            "nuPosicionCandidato": 0.0,
            "txCargoEleccion": [
                "ALCALDE DISTRITAL"
            ],
            "idCandidato": 171084.0,
            "idProcesoElectoral": 113.0,
            "documentosComplementarios": null
        },
        {
            "idExpediente": 154369.0,
            "idTipoEleccion": 6.0,
            "txCodExpedienteExt": "ERM.2022006827",
            "txNombres": "BEATRIZ EUGENIA",
            "txApellidoPaterno": "ALBINO",
            "txApellidoMaterno": "COTOS",
            "txDocumentoIdentidad": "75725070",
            "txRutaArchivo": "/Assets/Fotos-HojaVida/142931.jpg",
            "txFeNacimiento": "13/11/2002",
            "txSexo": "FEMENINO",
            "idEstadosCandPer": 3.0,
            "txEstado": "INADMISIBLE",
            "txDesignado": "NO",
            "idOrganizacionPolitica": 2857.0,
            "idHojaVida": 142931.0,
            "txOrganizacionPolitica": "PARTIDO FRENTE DE LA ESPERANZA 2021",
            "txUbigeoPostula": "ANCASH",
            "nuPosicionCandidato": 1.0,
            "txCargoEleccion": [
                "REGIDOR DISTRITAL"
            ],
            "idCandidato": 171085.0,
            "idProcesoElectoral": 113.0,
            "documentosComplementarios": null
        },
        {
            "idExpediente": 154369.0,
            "idTipoEleccion": 6.0,
            "txCodExpedienteExt": "ERM.2022006827",
            "txNombres": "GLICERIO DEMETRIO",
            "txApellidoPaterno": "FLORES",
            "txApellidoMaterno": "SARMIENTO",
            "txDocumentoIdentidad": "32394144",
            "txRutaArchivo": "/Assets/Fotos-HojaVida/142932.jpg",
            "txFeNacimiento": "08/10/1969",
            "txSexo": "MASCULINO",
            "idEstadosCandPer": 3.0,
            "txEstado": "INADMISIBLE",
            "txDesignado": "NO",
            "idOrganizacionPolitica": 2857.0,
            "idHojaVida": 142932.0,
            "txOrganizacionPolitica": "PARTIDO FRENTE DE LA ESPERANZA 2021",
            "txUbigeoPostula": "ANCASH",
            "nuPosicionCandidato": 2.0,
            "txCargoEleccion": [
                "REGIDOR DISTRITAL"
            ],
            "idCandidato": 171086.0,
            "idProcesoElectoral": 113.0,
            "documentosComplementarios": null
        },
        {
            "idExpediente": 154369.0,
            "idTipoEleccion": 6.0,
            "txCodExpedienteExt": "ERM.2022006827",
            "txNombres": "LIZ LOANA",
            "txApellidoPaterno": "PEREZ",
            "txApellidoMaterno": "VACAS",
            "txDocumentoIdentidad": "74946605",
            "txRutaArchivo": "/Assets/Fotos-HojaVida/142933.jpg",
            "txFeNacimiento": "20/06/1997",
            "txSexo": "FEMENINO",
            "idEstadosCandPer": 3.0,
            "txEstado": "INADMISIBLE",
            "txDesignado": "NO",
            "idOrganizacionPolitica": 2857.0,
            "idHojaVida": 142933.0,
            "txOrganizacionPolitica": "PARTIDO FRENTE DE LA ESPERANZA 2021",
            "txUbigeoPostula": "ANCASH",
            "nuPosicionCandidato": 3.0,
            "txCargoEleccion": [
                "REGIDOR DISTRITAL"
            ],
            "idCandidato": 171087.0,
            "idProcesoElectoral": 113.0,
            "documentosComplementarios": null
        },
        {
            "idExpediente": 154369.0,
            "idTipoEleccion": 6.0,
            "txCodExpedienteExt": "ERM.2022006827",
            "txNombres": "ROBERTO PABLO",
            "txApellidoPaterno": "BEDON",
            "txApellidoMaterno": "CORTEZ",
            "txDocumentoIdentidad": "80169958",
            "txRutaArchivo": "/Assets/Fotos-HojaVida/142934.jpg",
            "txFeNacimiento": "27/09/1973",
            "txSexo": "MASCULINO",
            "idEstadosCandPer": 3.0,
            "txEstado": "INADMISIBLE",
            "txDesignado": "NO",
            "idOrganizacionPolitica": 2857.0,
            "idHojaVida": 142934.0,
            "txOrganizacionPolitica": "PARTIDO FRENTE DE LA ESPERANZA 2021",
            "txUbigeoPostula": "ANCASH",
            "nuPosicionCandidato": 4.0,
            "txCargoEleccion": [
                "REGIDOR DISTRITAL"
            ],
            "idCandidato": 171088.0,
            "idProcesoElectoral": 113.0,
            "documentosComplementarios": null
        },
        {
            "idExpediente": 154369.0,
            "idTipoEleccion": 6.0,
            "txCodExpedienteExt": "ERM.2022006827",
            "txNombres": "MIRELLA ANALI",
            "txApellidoPaterno": "REYES",
            "txApellidoMaterno": "BLAS",
            "txDocumentoIdentidad": "46350462",
            "txRutaArchivo": "/Assets/Fotos-HojaVida/142935.jpg",
            "txFeNacimiento": "07/06/1990",
            "txSexo": "FEMENINO",
            "idEstadosCandPer": 3.0,
            "txEstado": "INADMISIBLE",
            "txDesignado": "NO",
            "idOrganizacionPolitica": 2857.0,
            "idHojaVida": 142935.0,
            "txOrganizacionPolitica": "PARTIDO FRENTE DE LA ESPERANZA 2021",
            "txUbigeoPostula": "ANCASH",
            "nuPosicionCandidato": 5.0,
            "txCargoEleccion": [
                "REGIDOR DISTRITAL"
            ],
            "idCandidato": 171089.0,
            "idProcesoElectoral": 113.0,
            "documentosComplementarios": null
        }
    ],
    "expedienteRelacionadoDirecto": null,
    "expedienteRelacionadoProcesal": null
}