{
    "pageIndex": 0,
    "pageSize": 0,
    "count": 0.0,
    "messageLog": null,
    "data": [
        {
            "idHojaVida": 174580.0,
            "feNacimiento": "1967-03-22T00:00:00",
            "txSexo": "M",
            "designado": null,
            "idProcesoElectoral": 0.0,
            "numeroDocumento": "29313477",
            "nombreCompleto": "JOHN JESUS ZUÑIGA VALDIVIA",
            "estado": "EXCLUSION",
            "idOrganizacionPolitica": 2719.0,
            "organizacionPolitica": "MOVIMIENTO REGIONAL REVALORA",
            "numeroCandidato": 0.0,
            "rutaArchivo": "/Assets/Fotos-HojaVida/174580.jpg",
            "postulaDepartamento": "AREQUIPA",
            "postulaProvincia": "CASTILLA",
            "postulaDistrito": "ANDAGUA",
            "cargo": [
                "ALCALDE DISTRITAL"
            ],
            "nativo": "NO"
        },
        {
            "idHojaVida": 174581.0,
            "feNacimiento": "1959-05-14T00:00:00",
            "txSexo": "M",
            "designado": null,
            "idProcesoElectoral": 0.0,
            "numeroDocumento": "29467118",
            "nombreCompleto": "ISIDRO VICTOR CORRALES BEDOYA",
            "estado": "IMPROCEDENTE",
            "idOrganizacionPolitica": 2719.0,
            "organizacionPolitica": "MOVIMIENTO REGIONAL REVALORA",
            "numeroCandidato": 1.0,
            "rutaArchivo": "/Assets/Fotos-HojaVida/174581.jpg",
            "postulaDepartamento": "AREQUIPA",
            "postulaProvincia": "CASTILLA",
            "postulaDistrito": "ANDAGUA",
            "cargo": [
                "REGIDOR DISTRITAL"
            ],
            "nativo": "NO"
        },
        {
            "idHojaVida": 174582.0,
            "feNacimiento": "1994-12-01T00:00:00",
            "txSexo": "F",
            "designado": null,
            "idProcesoElectoral": 0.0,
            "numeroDocumento": "76776814",
            "nombreCompleto": "OLIVIA NATALY APAZA LAZARO",
            "estado": "INSCRITO",
            "idOrganizacionPolitica": 2719.0,
            "organizacionPolitica": "MOVIMIENTO REGIONAL REVALORA",
            "numeroCandidato": 2.0,
            "rutaArchivo": "/Assets/Fotos-HojaVida/174582.jpg",
            "postulaDepartamento": "AREQUIPA",
            "postulaProvincia": "CASTILLA",
            "postulaDistrito": "ANDAGUA",
            "cargo": [
                "REGIDOR DISTRITAL"
            ],
            "nativo": "NO"
        },
        {
            "idHojaVida": 174583.0,
            "feNacimiento": "1986-05-28T00:00:00",
            "txSexo": "M",
            "designado": null,
            "idProcesoElectoral": 0.0,
            "numeroDocumento": "44685327",
            "nombreCompleto": "JUSTO GERMAN HUISACAYNA HUAMANI",
            "estado": "INSCRITO",
            "idOrganizacionPolitica": 2719.0,
            "organizacionPolitica": "MOVIMIENTO REGIONAL REVALORA",
            "numeroCandidato": 3.0,
            "rutaArchivo": "/Assets/Fotos-HojaVida/174583.jpg",
            "postulaDepartamento": "AREQUIPA",
            "postulaProvincia": "CASTILLA",
            "postulaDistrito": "ANDAGUA",
            "cargo": [
                "REGIDOR DISTRITAL"
            ],
            "nativo": "NO"
        },
        {
            "idHojaVida": 174584.0,
            "feNacimiento": "1986-02-05T00:00:00",
            "txSexo": "F",
            "designado": null,
            "idProcesoElectoral": 0.0,
            "numeroDocumento": "45132437",
            "nombreCompleto": "LIZ ISABEL RANILLA CACERES",
            "estado": "INSCRITO",
            "idOrganizacionPolitica": 2719.0,
            "organizacionPolitica": "MOVIMIENTO REGIONAL REVALORA",
            "numeroCandidato": 4.0,
            "rutaArchivo": "/Assets/Fotos-HojaVida/174584.jpg",
            "postulaDepartamento": "AREQUIPA",
            "postulaProvincia": "CASTILLA",
            "postulaDistrito": "ANDAGUA",
            "cargo": [
                "REGIDOR DISTRITAL"
            ],
            "nativo": "NO"
        },
        {
            "idHojaVida": 174585.0,
            "feNacimiento": "1971-11-06T00:00:00",
            "txSexo": "M",
            "designado": null,
            "idProcesoElectoral": 0.0,
            "numeroDocumento": "29517138",
            "nombreCompleto": "ALCIDES CEVERO LASTARRIA LAZARO",
            "estado": "INSCRITO",
            "idOrganizacionPolitica": 2719.0,
            "organizacionPolitica": "MOVIMIENTO REGIONAL REVALORA",
            "numeroCandidato": 5.0,
            "rutaArchivo": "/Assets/Fotos-HojaVida/174585.jpg",
            "postulaDepartamento": "AREQUIPA",
            "postulaProvincia": "CASTILLA",
            "postulaDistrito": "ANDAGUA",
            "cargo": [
                "REGIDOR DISTRITAL"
            ],
            "nativo": "NO"
        }
    ],
    "totalPages": 0
}